dotchatbot/dcb.py
dotchatbot/client/_anthropic.py
dotchatbot/client/_google.py
dotchatbot/client/_openai.py
dotchatbot/client/factory.py
dotchatbot/client/services.py
dotchatbot/input/parser.py
dotchatbot/input/transformer.py
dotchatbot/output/file.py
dotchatbot/output/markdown.py
dotchatbot-0.11.0.dist-info/licenses/LICENSE
dotchatbot-0.11.0.dist-info/METADATA
dotchatbot-0.11.0.dist-info/WHEEL
dotchatbot-0.11.0.dist-info/entry_points.txt
dotchatbot-0.11.0.dist-info/top_level.txt
dotchatbot-0.11.0.dist-info/RECORD
