Metadata-Version: 2.4
Name: dotchatbot
Version: 0.11.0
Summary: Chatbot CLI
Author-email: Brian Payne <bwpayne@gmail.com>
Project-URL: Homepage, https://github.com/bayne/dotchatbot
Classifier: Programming Language :: Python :: 3 :: Only
Classifier: Programming Language :: Python :: 3.11
Requires-Python: >=3.11
License-File: LICENSE
Requires-Dist: anthropic
Requires-Dist: click
Requires-Dist: google-genai
Requires-Dist: keyring
Requires-Dist: click-extra
Requires-Dist: pygments-ansi-color
Requires-Dist: rich
Requires-Dist: lark
Requires-Dist: openai
Dynamic: license-file
